Workbook

Sheet 基本設定
B2: 基本設定（最初にここを入力してください）
B3: 黄色のセルを入力すると、すべての見積書シートに自動で反映されます。
B5: ■ 発行者情報
B6: 会社名 | C6: 【会社名】 | E6: ← 例：株式会社〇〇
B7: 住所 | C7: 〒000-0000 【住所】 | E7: ← 例：〒150-0001 東京都渋谷区〇〇1-2-3
B8: 電話番号 | C8: 000-0000-0000
B9: メールアドレス | C9: 【メールアドレス】
B10: 担当者名 | C10: 【担当者名】
B11: 振込先 | C11: 【銀行名・支店名・種別・口座番号・口座名義】 | E11: ← 追加ご発注が発生した場合のみ使用します
B13: ■ 宛先・見積情報
B14: 宛先（お客様名） | C14: 〇〇〇〇 | E14: ← 相手ごとに書き換えてください
B15: 敬称 | C15: 御中 | E15: ← 法人＝御中／個人＝様
B16: 発行日 | C16: 2026年8月23日
B17: 見積番号 | C17: MG-2026-0001 | E17: ← 相手ごとに連番で振ってください
B18: 見積有効期限 | C18: 発行日より30日間
B19: 納期 | C19: ご発注後 約4〜6週間（ヒアリング完了より起算）
B21: ■ 計算条件
B22: 消費税率 | C22: 0.1 | E22: ← 税率が変わった場合はここだけ変更
B23: 通常価格（4話＋総集編・税別） | C23: 250000 | E23: ← 無料提供の定価。備考の記載にも使われます
B25: 凡例
B26: 黄色のセル | C26: 入力欄。ここだけ書き換えてください。
B27: 青文字 | C27: 手入力の値。
B28: 緑文字 | C28: 他シートを参照している値。直接書き換えないでください。
B29: 黒文字 | C29: 自動計算されるセル。触らないでください。
B31: 使い方
B32: ① このシートの黄色いセルを埋める（会社情報は一度だけ。宛先・見積番号は相手ごとに変更）
B33: ② 「見積書（無料制作）」シートを印刷／PDF出力して相手に送付する
B34: ③ 追加のご依頼が発生したら「見積書（追加オプション）」シートの数量欄に数を入れて送付する
B35: ④ 単価を変えたいときは「料金表」シートを編集する（追加オプション見積書に自動反映）

Sheet 見積書（無料制作）
B2: 御 見 積 書
B4: =基本設定!$C$14&" "&基本設定!$C$15 -> 〇〇〇〇 御中 | F4: 発行日 | G4: =基本設定!$C$16 -> 2026年8月23日
F5: 見積番号 | G5: =基本設定!$C$17 -> MG-2026-0001
B6: 下記の通りお見積り申し上げます。
E7: =基本設定!$C$6 -> 【会社名】
B8: 件 名 | C8: 社長ショートドラマ制作 全4話＋総集編 一式 | E8: =基本設定!$C$7 -> 〒000-0000 【住所】
B9: 有効期限 | C9: =基本設定!$C$18 -> 発行日より30日間 | E9: ="TEL："&基本設定!$C$8 -> TEL：000-0000-0000
B10: 納 期 | C10: =基本設定!$C$19 -> ご発注後 約4〜6週間（ヒアリング完了より起算） | E10: ="Email："&基本設定!$C$9 -> Email：【メールアドレス】
B11: お支払条件 | C11: 本見積は無償提供のため、お支払いはございません | E11: ="担当："&基本設定!$C$10 -> 担当：【担当者名】
B13: 御 見 積 金 額（税込） | E13: =G26 -> 0
B15: No. | C15: 品目・仕様 | D15: 数量 | E15: 単位 | F15: 単価 | G15: 金額
B16: 1 | C16: 企画・構成（全4話＋総集編／エピソード設計・構成台本） | D16: 1 | E16: 式 | F16: 40000 | G16: =D16*F16 -> 40000
B17: 2 | C17: 脚本制作（本編 全4話／ナレーション・セリフ・テロップ原稿） | D17: 4 | E17: 話 | F17: 15000 | G17: =D17*F17 -> 60000
B18: 3 | C18: 映像制作・編集（本編 全4話／AI映像生成・カット編集） | D18: 4 | E18: 話 | F18: 25000 | G18: =D18*F18 -> 100000
B19: 4 | C19: 総集編 制作・編集（1本） | D19: 1 | E19: 本 | F19: 25000 | G19: =D19*F19 -> 25000
B20: 5 | C20: テロップ挿入・BGM・効果音・仕上げ | D20: 1 | E20: 式 | F20: 15000 | G20: =D20*F20 -> 15000
B21: 6 | C21: 各SNS向け書き出し・納品（Instagram / TikTok / YouTube Shorts） | D21: 1 | E21: 式 | F21: 5000 | G21: =D21*F21 -> 5000
B22: 7 | C22: 修正対応（軽微修正 1回分） | D22: 1 | E22: 回 | F22: 5000 | G22: =D22*F22 -> 5000
B23: 8 | C23: 特別ご協力割引（本企画へのご参加条件のご履行を条件とする全額割引） | D23: 1 | E23: 式 | F23: =-SUM(G16:G22) -> -250000 | G23: =D23*F23 -> -250000
C24: 小 計（税別） | G24: =SUM(G16:G23) -> 0
C25: ="消費税（"&TEXT(基本設定!$C$22,"0%")&"）" -> 消費税（10%） | G25: =ROUND(G24*基本設定!$C$22,0) -> 0
C26: 合計金額（税込） | G26: =G24+G25 -> 0
B28: 備 考
B29: ※本見積書は、下記4条件のご履行を前提とした特別無償提供です。
B30: ①納品後7日以内に、ご本人アカウントにて投稿（Instagram「共同投稿者」機能で弊社アカウントを共同投稿者に設定／6ヶ月間の掲載継続）
B31: ②キャプションへの制作クレジット記載および弊社公式アカウントのタグ付け・メンション
B32: ③第1話公開時・総集編公開時の計2回、ストーリーズでのご紹介（弊社アカウントのメンション付き）
B33: ④完成動画の弊社二次利用（実績紹介・公式アカウントでの再投稿・営業資料・広告素材）のご許可
B34: ="※上記条件が履行されない場合、通常価格 "&TEXT(基本設定!$C$23,"¥#,##0")&"（税別）を申し受ける場合がございます。" -> ※上記条件が履行されない場合、通常価格 ¥250,000（税別）を申し受ける場合がございます。
B35: ※無償修正は納品後1回・軽微修正のみとし、納品後3日以内に一括でご依頼ください。範囲を超える修正は「料金表」に基づき別途お見積りいたします。
B36: 【軽微修正に含まれるもの】テロップの誤字・表記ゆれ／事実誤認の訂正／BGM・効果音の音量調整／尺の微調整（±3秒程度）／ご提供済み素材の差し替え
B37: 【別途お見積りとなるもの】構成・脚本の変更／シーン・カットの作り直し／登場人物のビジュアル変更／演出方向の変更／全体の作り直し
B38: ※脚本のご確認をもって内容の確定といたします。映像制作着手後の構成変更は別途お見積りとなります。
B39: ※確認のご依頼から3営業日以内にご返信がない場合は、ご承認いただいたものとみなし次工程へ進行いたします。
B40: ※素材（お写真・ロゴ等）のご提出はご依頼から7日以内にお願いいたします。2週間ご連絡が取れない場合はいったん制作終了とし、再開は別途お見積りといたします。
B41: ※本ドラマの映像はAIにより生成しております。登場人物は実在の人物ではありません。ご本人のお写真を使用する場合は事前にご相談いたします。
B42: ※エピソード内の実績・数値等、事実関係のご確認はご本人にてお願いいたします。
B43: ※制作途中でご中止となった場合、制作済みデータの権利は弊社に帰属し、公開はご遠慮いただきます。

Sheet 見積書（追加オプション）
B2: 御 見 積 書
B4: =基本設定!$C$14&" "&基本設定!$C$15 -> 〇〇〇〇 御中 | F4: 発行日 | G4: =基本設定!$C$16 -> 2026年8月23日
F5: 見積番号 | G5: =基本設定!$C$17 -> MG-2026-0001
B6: 下記の通りお見積り申し上げます。
E7: =基本設定!$C$6 -> 【会社名】
B8: 件 名 | C8: 社長ショートドラマ制作 追加オプション | E8: =基本設定!$C$7 -> 〒000-0000 【住所】
B9: 有効期限 | C9: =基本設定!$C$18 -> 発行日より30日間 | E9: ="TEL："&基本設定!$C$8 -> TEL：000-0000-0000
B10: 納 期 | C10: =基本設定!$C$19 -> ご発注後 約4〜6週間（ヒアリング完了より起算） | E10: ="Email："&基本設定!$C$9 -> Email：【メールアドレス】
B11: お支払条件 | C11: 納品後 翌月末までに指定口座へお振込み（振込手数料は貴社ご負担） | E11: ="担当："&基本設定!$C$10 -> 担当：【担当者名】
B13: 御 見 積 金 額（税込） | E13: =G25 -> 0
B15: No. | C15: 品目・仕様 | D15: 数量 | E15: 単位 | F15: 単価 | G15: 金額
B16: 1 | C16: =料金表!$C$4 -> 社長ショートドラマ 4話＋総集編パッケージ | D16: 0 | E16: =料金表!$D$4 -> 式 | F16: =料金表!$E$4 -> 250000 | G16: =D16*F16 -> 0
B17: 2 | C17: =料金表!$C$5 -> 追加話数の制作 | D17: 0 | E17: =料金表!$D$5 -> 話 | F17: =料金表!$E$5 -> 50000 | G17: =D17*F17 -> 0
B18: 3 | C18: =料金表!$C$6 -> 構成・脚本からの作り直し | D18: 0 | E18: =料金表!$D$6 -> 話 | F18: =料金表!$E$6 -> 30000 | G18: =D18*F18 -> 0
B19: 4 | C19: =料金表!$C$7 -> シーン再生成 | D19: 0 | E19: =料金表!$D$7 -> カット | F19: =料金表!$E$7 -> 5000 | G19: =D19*F19 -> 0
B20: 5 | C20: =料金表!$C$8 -> 追加修正（軽微修正・2回目以降） | D20: 0 | E20: =料金表!$D$8 -> 回 | F20: =料金表!$E$8 -> 10000 | G20: =D20*F20 -> 0
B21: 6 | C21: =料金表!$C$9 -> 横型・正方形など別比率の書き出し | D21: 0 | E21: =料金表!$D$9 -> 本 | F21: =料金表!$E$9 -> 5000 | G21: =D21*F21 -> 0
B22: 7 | C22: 特急対応割増（ご依頼から72時間以内の納品／上記小計の50%） | D22: 0 | E22: 式 | F22: =ROUND(SUM(G16:G21)*0.5,0) -> 0 | G22: =D22*F22 -> 0
C23: 小 計（税別） | G23: =SUM(G16:G22) -> 0
C24: ="消費税（"&TEXT(基本設定!$C$22,"0%")&"）" -> 消費税（10%） | G24: =ROUND(G23*基本設定!$C$22,0) -> 0
C25: 合計金額（税込） | G25: =G23+G24 -> 0
B27: 備 考・ご記入方法
B28: ※黄色のセル（数量欄）にご希望の数量をご入力ください。金額・小計・消費税・合計は自動で計算されます。
B29: ※単価は「料金表」シートと連動しています。単価を変更する場合は「料金表」シートをご編集ください。
B30: ※特急対応割増は、数量欄に「1」を入力すると項番1〜6の小計の50%が加算されます。
B32: 【記入例】追加修正を2回、シーン再生成を3カットご依頼の場合
B33: 項番5「追加修正（軽微修正・2回目以降）」の数量欄に「2」→ 金額 ¥20,000
B34: 項番4「シーン再生成」の数量欄に「3」→ 金額 ¥15,000
B35: 小計 ¥35,000 ／ 消費税 ¥3,500 ／ 合計 ¥38,500 が自動表示されます
B37: ※無償制作分（全4話＋総集編）に含まれる範囲を超えるご依頼が対象です。
B38: ※作業着手はご承認のご返信をいただいた後となります。
B39: ※お支払いは納品後、翌月末までに指定口座へお振込みをお願いいたします。
B40: ※本見積の有効期限は発行日より30日間です。

Sheet 料金表
B1: 追加オプション 料金表（税別）
B2: 黄色の単価セルを変更すると「見積書（追加オプション）」シートに自動反映されます。
B3: No. | C3: 項目 | D3: 単位 | E3: 単価（税別） | F3: 備考
B4: 1 | C4: 社長ショートドラマ 4話＋総集編パッケージ | D4: 式 | E4: 250000 | F4: 企画・脚本・映像制作・編集・納品まで一式（有料でお受けする場合の通常価格）
B5: 2 | C5: 追加話数の制作 | D5: 話 | E5: 50000 | F5: 第5話以降。企画・脚本・映像制作込み
B6: 3 | C6: 構成・脚本からの作り直し | D6: 話 | E6: 30000 | F6: 映像制作着手後の構成変更・脚本の書き直し
B7: 4 | C7: シーン再生成 | D7: カット | E7: 5000 | F7: 1カットあたり。既存構成のまま映像のみ差し替え
B8: 5 | C8: 追加修正（軽微修正・2回目以降） | D8: 回 | E8: 10000 | F8: 納品後1回目の軽微修正は無償。2回目以降が対象
B9: 6 | C9: 横型・正方形など別比率の書き出し | D9: 本 | E9: 5000 | F9: 1本あたり。16:9／1:1 などへのリサイズ書き出し
B10: 7 | C10: 特急対応割増（ご依頼から72時間以内の納品） | D10: 式 | E10: 対象小計の50% | F10: 見積書シート側で自動計算されます（単価の手入力は不要）
B12: 料金設定の考え方（社内メモ・相手には渡さないでください）
B13: ・通常価格 250,000円は「4話＋総集編」を有料で受注する場合の価格。無料提供の価値を相手に示すための基準値でもある。
B14: ・追加修正 10,000円/回は、金額そのものより「無限に依頼できない」ことを示すための設定。安すぎると抑止にならず、高すぎると角が立つ水準。
B15: ・構成・脚本からの作り直し 30,000円/話は、映像制作着手後の手戻りコストに相当。ここを無料にすると際限なく巻き戻される。
B16: ・断るのではなく「有料でお受けできます」と選ばせる形にすることで、細かい注文が売上に変わる。値引きはしない。
B17: ・相手によって単価を変えない。スムーズに進めてくれた方が損をする運用にすると、紹介が止まる。
